imagine/__init__.py
imagine/client.py
imagine/features/__init__.py
imagine/features/generations/__init__.py
imagine/features/generations/handler.py
imagine/features/generations/style_ids.py
imagine/features/generations/variations/__init__.py
imagine/features/generations/variations/handler.py
imagine/features/image_remix/__init__.py
imagine/features/image_remix/controls.py
imagine/features/image_remix/handler.py
imagine/features/image_remix/style_ids.py
imagine/features/in_painting/__init__.py
imagine/features/in_painting/handler.py
imagine/features/in_painting/style_ids.py
imagine/features/super_resolution/__init__.py
imagine/features/super_resolution/handler.py
imagine/features/super_resolution/style_ids.py
imagine/models/__init__.py
imagine/models/image.py
imagine/models/response.py
imagine/models/status.py
imagine/remote/__init__.py
imagine/remote/http_client.py
imagine/remote/_imagine/__init__.py
imagine/remote/_imagine/http_client.py
imagine/remote/rest/__init__.py
imagine/remote/rest/http_client.py
imagine/styles/__init__.py
imagine/type/__init__.py
imagine/type/multipart.py
imagine/utils/__init__.py
imagine/utils/error/__init__.py
imagine/utils/error/checker.py
imagine/utils/file/__init__.py
imagine/utils/file/read.py
imagine/utils/imports/__init__.py
imagine/utils/imports/dynamic.py
imagine/utils/parameter/__init__.py
imagine/utils/parameter/checker.py
imagine/utils/parameter/multipart.py
imaginesdk-1.0.0b4.dist-info/LICENSE
imaginesdk-1.0.0b4.dist-info/METADATA
imaginesdk-1.0.0b4.dist-info/WHEEL
imaginesdk-1.0.0b4.dist-info/top_level.txt
imaginesdk-1.0.0b4.dist-info/RECORD
