Metadata-Version: 2.1
Name: imaginesdk
Version: 1.0.0b4
Summary: Python client library for Imagine API
Home-page: https://github.com/Vyro-ai/imagine-sdk-python
Author: Vyro
Author-email: api.imagine@vyro.ai
License: Apache 2
Classifier: Intended Audience :: Developers
Classifier: License :: OSI Approved :: Apache Software License
Classifier: Programming Language :: Python :: 3
Classifier: Programming Language :: Python :: 3.6
Classifier: Programming Language :: Python :: 3.7
Classifier: Programming Language :: Python :: 3.8
Classifier: Programming Language :: Python :: 3.9
Classifier: Programming Language :: Python :: 3.10
Classifier: Operating System :: OS Independent
Requires-Python: >=3.6
License-File: LICENSE
Requires-Dist: requests
Provides-Extra: all
Requires-Dist: numpy ; extra == 'all'
Requires-Dist: Pillow ; extra == 'all'
